AUTHORS
ChangeLog
LICENSE
MANIFEST.in
README.rst
requirements.txt
run_tests.sh
setup.cfg
setup.py
test-requirements.txt
tox.ini
evproc/__init__.py
evproc/decorator.py
evproc/event.py
evproc/exc.py
evproc/processor.py
evproc.egg-info/PKG-INFO
evproc.egg-info/SOURCES.txt
evproc.egg-info/dependency_links.txt
evproc.egg-info/not-zip-safe
evproc.egg-info/pbr.json
evproc.egg-info/requires.txt
evproc.egg-info/top_level.txt
tests/__init__.py
tests/unit/__init__.py
tests/unit/test_decorator.py
tests/unit/test_event.py
tests/unit/test_exc.py
tests/unit/test_processor.py